data_formatting_help/__init__.py
data_formatting_help/formatter.py
tests/__init__.py
tests/test_formatter.py
data_formatting_help-1.0.2.dist-info/LICENSE
data_formatting_help-1.0.2.dist-info/METADATA
data_formatting_help-1.0.2.dist-info/WHEEL
data_formatting_help-1.0.2.dist-info/top_level.txt
data_formatting_help-1.0.2.dist-info/RECORD
